{
    "name": "EVA-08γ -Operation Yamato-",
    "ID": "CB01-037",
    "set": "CB01",
    "image": "images/CB01/CB01-037.png",
    "color": [
        "Green"
    ],
    "cost": "5",
    "reduction": [
        "green",
        "green",
        "red",
        "red"
    ],
    "symbols": [
        "green"
    ],
    "cardType": "SPIRIT",
    "subType": [
        "GOLEM",
        "EVA-08",
        "WILLE"
    ],
    "rarity": "R",
    "effects": [
        {
            "levels": [
                1,
                2,
                3
            ],
            "condition": "N/A",
            "keywords": [
                {
                    "keyword": "A.T. Field",
                    "target": null,
                    "value": null
                }
            ],
            "details": "N/A",
            "steps": []
        },
        {
            "levels": [
                2,
                3
            ],
            "condition": "While This Spirit Attacks",
            "keywords": [
                {
                    "keyword_name": "Gale",
                    "keyword_modifier": 1
                }
            ],
            "details": "N/A",
            "steps": []
        },
        {
            "levels": [
                2,
                3
            ],
            "condition": "When This Spirit Attacks",
            "keywords": [],
            "details": "If you control a Mari nexus, select one of your EVA-02 spirits and refresh it.",
            "steps": []
        }
    ],
    "core_requirements": [
        {
            "level": 1,
            "battlePoints": 4000,
            "cores": 1
        },
        {
            "level": 2,
            "battlePoints": 5000,
            "cores": 3
        },
        {
            "level": 3,
            "battlePoints": 7000,
            "cores": 5
        }
    ]
}