{
    "name": "Earth Spider Demon",
    "ID": "BSS01-049",
    "set": "BSS01",
    "image": "images/BSS01/BSS01-049.png",
    "color": [
        "Purple"
    ],
    "cost": "4",
    "reduction": [
        "purple",
        "purple"
    ],
    "symbols": [
        "purple"
    ],
    "cardType": "SPIRIT",
    "subType": [
        "FAMILIAR"
    ],
    "rarity": "UC",
    "effects": [
        {
            "levels": [
                1,
                2
            ],
            "condition": "When This Spirit Attacks",
            "keywords": [],
            "details": "If this spirit has a on it, select one of your opponent's spirits. Remove a core from it and place it into their reserve.",
            "steps": []
        }
    ],
    "core_requirements": [
        {
            "level": 1,
            "battlePoints": 2000,
            "cores": 1
        },
        {
            "level": 2,
            "battlePoints": 4000,
            "cores": 3
        }
    ]
}